tempylate/__init__.py
tempylate/builtins.py
tempylate/exceptions.py
tempylate/manager.py
tempylate/py.typed
tempylate/template.py
tempylate/types.py
tempylate/utils.py
tempylate-0.1.3.dist-info/LICENSE
tempylate-0.1.3.dist-info/METADATA
tempylate-0.1.3.dist-info/WHEEL
tempylate-0.1.3.dist-info/top_level.txt
tempylate-0.1.3.dist-info/RECORD
