Metadata-Version: 2.1
Name: tempylate
Version: 0.1.3
Summary: Little, lightweight and fast template engine.
Home-page: UNKNOWN
Author: tasuren
Author-email: tasuren@aol.com
License: MIT
Project-URL: Documentation, https://tempylate.readthedocs.io/
Project-URL: Donate, https://www.buymeacoffee.com/tasuren
Project-URL: Source Code, https://github.com/tasuren/tempylate
Project-URL: Chat, https://discord.gg/kfMwZUyGFG
Keywords: template engine
Platform: UNKNOWN
Classifier: Programming Language :: Python :: 3.10
Classifier: Topic :: Text Processing :: Markup :: HTML
Classifier: Typing :: Typed
Requires-Python: >=3.10.0
License-File: LICENSE
